ThrustRTC/Context.py
ThrustRTC/Copying.py
ThrustRTC/DVTuple.py
ThrustRTC/DVVector.py
ThrustRTC/DeviceViewable.py
ThrustRTC/FakeVectors.py
ThrustRTC/Functor.py
ThrustRTC/Merging.py
ThrustRTC/Native.py
ThrustRTC/PrefixSums.py
ThrustRTC/PyThrustRTC.dll
ThrustRTC/Reductions.py
ThrustRTC/Reordering.py
ThrustRTC/Searching.py
ThrustRTC/Sorting.py
ThrustRTC/Transformations.py
ThrustRTC/__init__.py
ThrustRTC/cffi.py
ThrustRTC/libPyThrustRTC.so
ThrustRTC/utils.py
ThrustRTC-0.3.20.dist-info/METADATA
ThrustRTC-0.3.20.dist-info/WHEEL
ThrustRTC-0.3.20.dist-info/top_level.txt
ThrustRTC-0.3.20.dist-info/RECORD
